rlane_tf2mon-1.0.44.dist-info/METADATA
rlane_tf2mon-1.0.44.dist-info/WHEEL
rlane_tf2mon-1.0.44.dist-info/entry_points.txt
rlane_tf2mon-1.0.44.dist-info/licenses/LICENSE
tf2mon/__init__.py
tf2mon/__main__.py
tf2mon/_logger.py
tf2mon/admin.py
tf2mon/baselayout.py
tf2mon/chat.py
tf2mon/cli.py
tf2mon/conlog.py
tf2mon/control.py
tf2mon/controller.py
tf2mon/controls/__init__.py
tf2mon/controls/chats.py
tf2mon/controls/gridlayout.py
tf2mon/controls/help.py
tf2mon/controls/kicklast.py
tf2mon/controls/kicks.py
tf2mon/controls/logger.py
tf2mon/controls/misc.py
tf2mon/controls/msgqueue.py
tf2mon/controls/msgqueues.py
tf2mon/controls/singlestep.py
tf2mon/controls/sortorder.py
tf2mon/controls/spams.py
tf2mon/controls/userpanel.py
tf2mon/cycle.py
tf2mon/data/exclude.txt
tf2mon/data/racist.txt
tf2mon/data/weapons.csv
tf2mon/database.py
tf2mon/fkey.py
tf2mon/game/__init__.py
tf2mon/game/capture.py
tf2mon/game/chat.py
tf2mon/game/connected.py
tf2mon/game/kill.py
tf2mon/game/lobby.py
tf2mon/game/misc.py
tf2mon/game/perk.py
tf2mon/game/status.py
tf2mon/game/suicide.py
tf2mon/gameevent.py
tf2mon/gameplay.py
tf2mon/layouts/__init__.py
tf2mon/layouts/chat.py
tf2mon/layouts/default.py
tf2mon/layouts/full.py
tf2mon/layouts/tall.py
tf2mon/layouts/tallchat.py
tf2mon/layouts/wide.py
tf2mon/monitor.py
tf2mon/msgqueue.py
tf2mon/pkg.py
tf2mon/player.py
tf2mon/racist.py
tf2mon/regex.py
tf2mon/role.py
tf2mon/scoreboard.py
tf2mon/spammer.py
tf2mon/steamid.py
tf2mon/steamplayer.py
tf2mon/steamweb.py
tf2mon/texttable.py
tf2mon/ui.py
tf2mon/user.py
tf2mon/users.py
rlane_tf2mon-1.0.44.dist-info/RECORD
