Metadata-Version: 2.1
Name: rlane-tf2mon
Version: 1.0.44
Summary: Team Fortress 2 Console Monitor
Keywords: tf2,team-fortress-2,steam,valve,bots,cathook
Author-Email: Russel Lane <russel@rlane.com>
License: MIT
Classifier: Development Status :: 3 - Alpha
Classifier: Intended Audience :: End Users/Desktop
Classifier: License :: OSI Approved :: MIT License
Classifier: Programming Language :: Python :: 3
Classifier: Topic :: Games/Entertainment :: First Person Shooters
Project-URL: Homepage, https://github.com/russellane/tf2mon
Requires-Python: >=3.10
Requires-Dist: fuzzywuzzy>=0.18.0
Requires-Dist: humanize>=4.10.0
Requires-Dist: loguru>=0.7.2
Requires-Dist: python-levenshtein>=0.26.0
Requires-Dist: rlane-libcli>=1.0.6
Requires-Dist: rlane-libcurses>=1.0.7
Requires-Dist: steam>=1.4.4
Requires-Dist: xdg>=6.0.0
